tomcatmanager/__init__.py
tomcatmanager/__main__.py
tomcatmanager/interactive_tomcat_manager.py
tomcatmanager/models.py
tomcatmanager/py.typed
tomcatmanager/tomcat_manager.py
tomcatmanager/templates/__init__.py
tomcatmanager/templates/theme.toml
tomcatmanager/themes/__init__.py
tomcatmanager/themes/default-dark.toml
tomcatmanager/themes/default-light.toml
tomcatmanager-7.0.1.dist-info/LICENSE
tomcatmanager-7.0.1.dist-info/METADATA
tomcatmanager-7.0.1.dist-info/WHEEL
tomcatmanager-7.0.1.dist-info/entry_points.txt
tomcatmanager-7.0.1.dist-info/top_level.txt
tomcatmanager-7.0.1.dist-info/RECORD
