Metadata-Version: 2.1
Name: tomcatmanager
Version: 7.0.1
Summary: A command line tool and python library for managing a tomcat server.
Author-email: Jared Crapo <jared@kotfu.net>
License: Copyright (c) 2007 Jared Crapo
Project-URL: homepage, https://github.com/tomcatmanager/tomcatmanager
Project-URL: documentation, https://tomcatmanager.readthedocs.io
Project-URL: repository, https://github.com/tomcatmanager/tomcatmanager
Keywords: java,tomcat,command line
Classifier: Development Status :: 5 - Production/Stable
Classifier: Environment :: Console
Classifier: Operating System :: OS Independent
Classifier: Topic :: System :: Systems Administration
Classifier: Topic :: Utilities
Classifier: Topic :: Software Development :: Libraries :: Python Modules
Classifier: Intended Audience :: Developers
Classifier: Intended Audience :: System Administrators
Classifier: License :: OSI Approved :: MIT License
Classifier: Programming Language :: Python :: 3 :: Only
Classifier: Programming Language :: Python :: 3.8
Classifier: Programming Language :: Python :: 3.9
Classifier: Programming Language :: Python :: 3.10
Classifier: Programming Language :: Python :: 3.11
Classifier: Programming Language :: Python :: 3.12
Requires-Python: >=3.8
License-File: LICENSE
Requires-Dist: cmd2 <3,>=2.4.3
Requires-Dist: requests <3,>=2
Requires-Dist: appdirs
Requires-Dist: tomlkit
Requires-Dist: rich
Requires-Dist: rich-argparse
Requires-Dist: importlib-resources >=5.0 ; python_version < "3.9"
Provides-Extra: dev
Requires-Dist: build ; extra == 'dev'
Requires-Dist: pytest ; extra == 'dev'
Requires-Dist: pytest-mock ; extra == 'dev'
Requires-Dist: tox ; extra == 'dev'
Requires-Dist: codecov ; extra == 'dev'
Requires-Dist: pytest-cov ; extra == 'dev'
Requires-Dist: ruff ; extra == 'dev'
Requires-Dist: pylint ; extra == 'dev'
Requires-Dist: setuptools-scm ; extra == 'dev'
Requires-Dist: wheel ; extra == 'dev'
Requires-Dist: twine ; extra == 'dev'
Requires-Dist: rope ; extra == 'dev'
Requires-Dist: invoke ; extra == 'dev'
Requires-Dist: sphinx <7 ; extra == 'dev'
Requires-Dist: sphinx-autobuild ; extra == 'dev'
Requires-Dist: sphinx-rtd-theme >1 ; extra == 'dev'
Requires-Dist: autodocsumm ; extra == 'dev'
Requires-Dist: doc8 ; extra == 'dev'
Requires-Dist: docutils ; extra == 'dev'
Provides-Extra: docs
Requires-Dist: sphinx ; extra == 'docs'
Requires-Dist: sphinx-autobuild ; extra == 'docs'
Requires-Dist: sphinx-rtd-theme ; extra == 'docs'
Requires-Dist: autodocsumm ; extra == 'docs'
Requires-Dist: doc8 ; extra == 'docs'
Requires-Dist: docutils ; extra == 'docs'
